{
  "posts": [
    {
      "id": 1,
      "heading": "How Business Consultants in Qatar Assist with Strategic Growth & Expansion",
      "content": "# Tax Business Consultants\nTax Business Consultants is among the top consultant companies in Qatar and offers business entities professional advice according to the expansion of their market. With our expertise within the industry, we understand the unique hurdles that businesses in Qatar encounter and devise workable strategies to attain positive and lasting results regardless of those hurdles. We make the expansion process faster, easier, and less stressful. That is why our team of experts is full of experienced professionals who are always ready and more than willing to help companies deal with complex marketing changes quickly.\n\n## Understanding Strategic Growth & Expansion\n\nStrategic growth arises from the contemplation of long-term objectives, intelligent decision-making and market analysis, and successful business operation efforts to maximize profit and sustainability. The success of any expansion depends on the applied knowledge, keeping track of the money laws, and, of course, planning finances. The right lever of knowledge will permit a business to utilize opportunities in Qatar’s economy to make a successful ascent.\n\n## Role of Consultant Companies in Qatar\n\nConsulting firms are significant advisors for companies that are looking into new markets, assessing risks, or achieving regulatory compliance. We are a foremost business consulting firm engaged in performing market trends, competition, and investment analysis. Our consultants have the expertise to help businesses make the right decisions, lower their risk, and increase the growth of the enterprise.\n\n## Business Setup in Qatar: A Growth Foundation\n\nStrong beginnings are the key to successful growth. Business formation in Qatar involves adhering to legal requirements, choosing the appropriate business structure, and securing required licenses. We facilitate this process by managing the documentation, government approvals, and company registration so that entrepreneurs can concentrate on their business operations.\n\nWe are condoned to prove to become a mark of prosperity. Our consulting services commence with company formation. Additionally, we assist in market research, improving operational efficiency, developing overarching strategies, and financial management. Our consultation services are specially designed for each client. We always provide fact-driven solutions for easing business growth without any hassles.\n\n## The Best Business Consultants in Qatar\n\nHaving the right business consultants in Qatar can make a huge difference towards achieving business expansion. We are a team of top management consultants, known for our competency in delivering research-based, actionable advice to help clients capitalize on opportunities and predict and avert possible challenges and issues. With this input, businesses can now plan effectively for the future in line with their vision and aspirations.\n\n## Your Trusted Partner in Business Expansion\n\nWe nurture business expansion and growth in Qatar. We are business and entrepreneurship partners with a strong interest in growing big through market analysis, regulatory frameworks, and fiscal finance plans. Our experts are here to serve your business in all stages. Our consulting activities assist companies to capitalize on opportunities, reduce their risks, and ensure their sustainable success in the vibrant Qatari market. With our business consulting services, you can take your business up a notch.",
      "image": "/images/blog-images/blog-image-1.webp"
    },
    {
      "heading": "Top Taxation Consultancy Services in Qatar: What You Need to Know",
      "content": "Taxation is an aspect paramount for good financial condition and compliance with any company. Qatar is also blossoming with various types of businesses and companies; hence, it has become imperative to have tax consultants. Tax Business Consultants, being one of the [best consultants in Qatar](https://www.taxbusinessconsultant.com/), specializes in the provision of consultancy services related to taxation that are intended to aid companies in their difficulties in dealing with tax laws and regulations.\n\n## **The Role of Tax Business Consultants in Qatar**\n\nTechnical changes in the law take place so often that we must keep informing our clients to update themselves. Our Qatar business consultants will take over the worries of regulatory compliance in a manner that ensures the minimization of the tax burden of the client company. We offer a variety of services from compliance solutions, tax advisory, regulatory advice, and strategic tax planning through which a business can have peace of mind with no concern for tax matters.\n\n## **Why Companies Require Specialized Taxation Consultancy**\n\nCompanies working in Qatar need to comply with rigorous tax measures, such as corporate taxation, withholding tax, and VAT management. In the absence of advisory, companies are at risk of facing legal prosecution or financial ineffectiveness. By collaborating with top [consultant companies in Qatar](https://eminentsoft.blogspot.com/2025/01/what-are-the-key-steps-to-establish-a-business-in-qatar.html), companies can acquire customized taxation recommendations that suit their financial objectives and regulatory needs.\n\n## **Tax Compliance and Business Setup**\n\nFor new companies, tax compliance starts right from the early stages of business setup in Qatar. We help companies set up their tax structure from the beginning so that they have a smooth registration process. We guide businesses in selecting the appropriate tax structures, obtaining required tax registrations, and meeting regulatory requirements so that they can run smoothly.\n\n### **Tax Planning and Optimization Strategies**\n\nEvery business seeks to maximize profits while maintaining compliance with tax laws. Through our business consulting and [taxation consultancy services](https://www.taxbusinessconsultant.com/about-us), we provide effective tax planning and optimization strategies. Our expertise helps businesses reduce tax burdens through legal tax-saving techniques, investment planning, and financial structuring. We focus on customized solutions that align with business objectives and industry-specific tax regulations.\n\n### **Managing Audits and Tax Disputes**\n\nTax audits and tax disputes may prove to be tricky for companies. With a professional tax consultant, companies are able to manage tax audits effectively and reduce risks. We offer skilled advice in preparing audit records, dealing with tax authorities, and resolving disputes in an effective manner. Our professionals ensure that businesses are transparent and compliant, avoiding the risk of penalties or legal action.\n\n### **Ensuring Efficient Business Operations**\n\nAt Tax Business Consultants, we transcend compliance by providing proactive tax services that facilitate business growth. Our consultancy services include VAT registration, corporate tax consultancy, international tax, and financial risk analysis. We recognize the specific challenges faced by businesses in Qatar and provide strategic solutions for long-term success.\n\nOwing to ever-changing laws, companies require specialist services to remain compliant and cost-effective. Engaging a trustworthy taxation consultant assists companies in evading legal penalties while enhancing financial effectiveness. Professional taxation advisory will greatly advance your [business formation in Qatar](https://www.taxbusinessconsultant.com/services). So, trust Tax Business Consultants to provide comprehensive tax solutions that help your business in Qatar.",
      "image": "https://images.unsplash.com/photo-1664575599618-8f6bd76fc670?q=80&w=1170&auto=format&fit=crop&ixlib=rb-4.0.3&ixid=M3wxMjA3fDB8MHxwaG90by1wYWdlfHx8fGVufDB8fHx8fA%3D%3D",
      "id": "1741850716955"
    },
    {
      "heading": "Maximizing Profits with the Top Consultants in Qatar",
      "content": "For the [business formation in Qatar](https://www.taxbusinessconsultant.com/), it is necessary to organize the finances, plan for complications, and set future goals. Tax Business Consultants assist organizations in carrying out their marketing campaigns by offering consulting services. Companies can count on getting professional advice whenever they need it, which helps them make money through good planning, smart tax strategies, and making their business run better.\n\n## **The Importance of Business Establishment in Qatar**\n\nTo start a business in Qatar, one needs to comply with certain legal and financial procedures. Doing business in Qatar starts with the best business form available, followed by securing the right approvals, as per the local law. Our extensive pool of experts provides a very smooth setup process for all entrepreneurs, thereby minimizing the risk and maximizing growth.\n\n## **The Role of Consulting Companies in Qatar**\n\nConsultancy firms play a vital role in increasing business productivity and profits. We are among the leading [consultant companies in Qatar](https://eminentsoft.blogspot.com/2025/01/what-are-the-key-steps-to-establish-a-business-in-qatar.html) that provide consultancy with market trends, risk management, and smooth operation recommendations. We work very closely with businesses and analyze obstacles to create tailored plans designed to improve productivity, reduce costs, and increase profits.\n\n## **How the Best Consultants in Qatar Support Business Growth**\n\nSelecting the appropriate consultants could play a very crucial role in the success of any organization. The top consultants in Qatar provide strategic advice, market research, and money management support. Our team at Tax Business Consultants analyzes account data, recommends cost-saving methods, and guides companies towards sustainable growth. Companies can enhance efficiency and profitability through our advice.\n\n### **Financial Planning and Cost Optimization**\n\nFinancial planning helps companies manage expenses and allocate resources in the most efficient possible way. We, being the [best consultants in Qatar](https://www.taxbusinessconsultant.com/about-us), help them set budgets and forecasts that identify areas where costs can be cut. By utilizing strategies, an opportunity opens for businesses to improve cash flow and reinvest into further growth opportunities.\n\n### **Regulatory Compliance and Risk Management**\n\nThere are several local laws and regulations that govern operations in Qatar. We advise businesses on legal requirements essential for the minimization of risks and losses arising from legal issues. Our teams of consultants have a firm understanding of policy and provide guidance on compliance to enable businesses to maintain a healthy legal and financial base.\n\n### **Strategic Growth and Expansion of Business**\n\nTo scale a business, one needs the correct strategy and market knowledge. Our team also advises on expansion projects, penetration of new markets, and the positioning of firms competitively. With such backing and support, firms can feel empowered to enter new doorways and truly grab the existing moment of the growing economy of Qatar.\n\n### **Taxation Consultancy Services for Financial Success**\n\nTaxation is one of the most important factors in deciding the profitability of a business. Effective tax planning and compliance can save companies money and penalties. Our [taxation consultancy services](https://www.taxbusinessconsultant.com/services) provide professional advice on corporate tax, VAT compliance, and financial planning. We assist businesses in minimizing their tax liabilities, ensuring that they comply with regulatory requirements while enhancing their bottom line.",
      "image": "https://images.unsplash.com/photo-1554224155-1696413565d3?q=80&w=1170&auto=format&fit=crop&ixlib=rb-4.0.3&ixid=M3wxMjA3fDB8MHxwaG90by1wYWdlfHx8fGVufDB8fHx8fA%3D%3D",
      "id": "1741884079479"
    },
    {
      "heading": "How PRO Services in Qatar Help Foreign Investors and Entrepreneurs",
      "content": "Investing and entering the ever-thriving business ambiance in Qatar is a very rewarding experience for foreign investors and entrepreneurs. Still, being able to cross the generally challenging landscape without a smooth guide will not be easy. Here is where our [PRO services in Qatar](https://www.taxbusinessconsultant.com/) come into play by simplifying business setup, ensuring compliance, and assisting in the coordination of government-related documentation.\n\n## **PRO Services in Business Setup**\n\nFor a business to be established, a lot of paperwork, approvals, and compliance with the laws in the respective regions are necessary. Tax Business Consultants, as top PRO service providers, help entrepreneurs to complete all the formalities with ease, right from company registration and licensing to visa processing and document attestation. Our experience ensures a trouble-free setup so that investors may focus on their business goals rather than bureaucratic hurdles.\n\n### **Legal Compliance and Licensing Support**\n\nEvery business in Qatar has to adhere to the government standards, including obtaining the required license and approvals. It is through our [PRO services Qatar](https://www.taxbusinessconsultant.com/about-us) that investors are updated on legal requirements so that their business operation is in line with the law. This proactive approach minimizes the risk of fines or penalties and fosters a smooth operational framework.\n\n### **Visa and Immigration Assistance**\n\nForeign investors and entrepreneurs generally need work and residence visas for themselves and their employees. With our PRO services, we take care of the whole procedure from visa application to renewal and cancellation. Therefore, migration is easier, and there is no need to wait for colleagues with unnecessary delays or legal issues in the business setup.\n\n### **Clearance and Attestation of Documents**\n\nEstablishing a company in Qatar involves many official documents to be verified and attested. We, Tax Business Consultants, being a trusted PRO service provider, ensure timely processing of documents associated with company formation, legal agreements, and government approvals. We are professionals in handling the administrative workload that limits the processing and, at the same time, boosts the operation's efficiency.\n\n### **Financial and Taxation Consultancy Services**\n\nThe subject and activities of companies in Qatar include adherence to the necessities of finances and tax laws. Our [taxation consultancy services](https://www.taxbusinessconsultant.com/about-us) make it possible for foreign investors to appreciate the tax regulations and optimize their financial strategies while making proper tax filings. This helps businesses maximize their profitability while being compliant with local tax laws.\n\n## **Streamlining Government Liaison and Corporate Services**\n\nThere is no business in Qatar without a touch of government interaction. PRO service providers act as contact representatives between corporations and government departments who facilitate everything from labor law compliance to trade licensing renewals. All this is designed to eliminate potential clogs in the way of business operations.\n\nEstablishing a company in Qatar could be a complicated process in the eyes of a foreign investor, but in the right direction with PRO services, it becomes easier. Beginning with documentation, legal compliance, and financial consultancy in professional assistance and smooth business practices, Tax Business Consultants, being the best [PRO service providers in Qatar](https://www.taxbusinessconsultant.com/services), deliver adequate services and solutions, helping entrepreneurs set up their presence in Qatar.",
      "image": "https://images.unsplash.com/photo-1552581234-26160f608093?q=80&w=1170&auto=format&fit=crop&ixlib=rb-4.0.3&ixid=M3wxMjA3fDB8MHxwaG90by1wYWdlfHx8fGVufDB8fHx8fA%3D%3D",
      "id": "1741889357560"
    },
    {
      "heading": "Building Financially Stable Startups Through Business Formation Services in Qatar",
      "content": "Starting a business in Qatar provides a great opportunity for entrepreneurs since its economy is thriving, investor-friendly policies are in place, and it is strategically located. Yet building an economically sustainable startup is quite complex and requires careful planning, acquaintance with the local regulations, and a well-placed financial strategy. Tax Business Consultants specializes in providing a wide range of business formation services and the [best pro service in Qatar](https://www.taxbusinessconsultant.com/) so that startups can establish a solid financial foundation in Qatar.\n\n## **The Importance of Financial Stability for Startups**\n\nMost startups fail because of bad financial management, non-compliance, or lack of planning. A proper financial framework is important for sustainability, investment, and efficient scaling of operations. The right business model structure and compliance with financial regulations require expert guidance. That is where our pro services come in, helping entrepreneurs manage the complexities of company formation and financial planning.\n\n## **How Business Formation Services Guarantee a Powerful Financial Beginning**\n\nForming a business in Qatar requires many processes such as legal registration, tax compliance, and financial structuring. Most new companies encounter several setbacks with such procedures, leading to unnecessary costs or delays in establishing the operation. Our proficiency in [pro services Qatar](https://eminentsoft.blogspot.com/2025/01/what-are-the-key-steps-to-establish-a-business-in-qatar.html) guarantees the establishment of any business in its operation while having an eye for long-term financial security.\n\n### **We can help in the following processes:**\n\n*   • Choose the right business format: LLC, partnership, or sole proprietorship.\n    \n\n*   • Compliance with all tax and financial requirements.\n    \n\n*   • Proper accounting and bookkeeping.\n    \n\n*   • Recommendations for access to funding and investment strategies.\n    \n\n*   • Understanding the regulatory framework of Qatar.\n    \n\nQatar law has explicitly defined the guiding principles of establishment, tax imposition, and reporting of financial performance, which are nested fundamentally within the Ministry of Economy and Commerce. Noncompliance with this regulation attracts a penalty and also financial instability. As one of the [best consultants in Qatar](https://www.taxbusinessconsultant.com/about-us), we give technical support to all start-ups on how to get all legal and financial compliance correct.\n\n### **Our Services Include**\n\n• Tax registration and filing compliance\n\n• Financial planning for long-term sustainability\n\n• Risk assessment and mitigation strategies\n\n• Securing funding and investments\n\n### **Role of Consultants in Start-Up Success**\n\nEarly phases of business building call for careful planning and strategizing, more specifically with financial planning, tax compliance, and risk management. By joining hands with consulting companies like us, a start-up gets exposure to professional wisdom, industry-based knowledge, and ongoing services.\n\nWith the help of professional business consulting firms, startups can:\n\n• Optimize their finances to reduce costs and risks associated\n\n• Tax effectiveness and financial reporting\n\n• Have an opportunity to access funding facilities and banking assistance\n\n• Emphasize growth and let the professionals manage compliance and financial planning.\n\n### **Collaborate with Tax Business consultants for a strong financial future**\n\nWe are one of the best [consultant companies in Qatar](https://www.taxbusinessconsultant.com/services) and provide business formation services to help new companies establish a sound financial footing in Qatar. By having profound knowledge of the country's laws, financial strategy, and the best practices that should be in any industry, we help our clients achieve sustainable success in Qatar.",
      "image": "https://images.unsplash.com/photo-1543269865-cbf427effbad?q=80&w=1170&auto=format&fit=crop&ixlib=rb-4.0.3&ixid=M3wxMjA3fDB8MHxwaG90by1wYWdlfHx8fGVufDB8fHx8fA%3D%3D",
      "id": "1741889401205"
    }
  ]
}